{"entropy": 77299523720177080618670366201064358918, "10": {"num_user": 100, "num_service": 41, "min_max_equal_weight": {"max_delay": 0.13737653104795397, "running_time": 10.008573532104492}}, "20": {"num_user": 100, "num_service": 41, "min_max_equal_weight": {"max_delay": 0.04926024113007868, "running_time": 11.008977890014648}}, "30": {"num_user": 100, "num_service": 41, "min_max_equal_weight": {"max_delay": 0.03460219546763534, "running_time": 12.01009750366211}}, "40": {"num_user": 100, "num_service": 41, "min_max_equal_weight": {"max_delay": 0.029170831325649984, "running_time": 13.010740280151367}}, "50": {"num_user": 100, "num_service": 41, "min_max_equal_weight": {"max_delay": 0.029170831325649984, "running_time": 15.012979507446289}}, "60": {"num_user": 100, "num_service": 41, "min_max_equal_weight": {"max_delay": 0.026570640637479, "running_time": 15.012502670288086}}, "70": {"num_user": 100, "num_service": 41, "min_max_equal_weight": {"max_delay": 0.01835992241503678, "running_time": 15.012502670288086}}, "80": {"num_user": 100, "num_service": 41, "min_max_equal_weight": {"max_delay": 0.012466191345243769, "running_time": 15.011787414550781}}, "90": {"num_user": 100, "num_service": 41, "min_max_equal_weight": {"max_delay": 0.012466191345243769, "running_time": 16.013145446777344}}, "100": {"num_user": 100, "num_service": 41, "min_max_equal_weight": {"max_delay": 0.01228117908405213, "running_time": 17.014026641845703}}}